firstclass_dotenv/__init__.py
firstclass_dotenv/main.py
tests/__init__.py
tests/test_1stclass_dotenv.py
firstclass_dotenv-0.0.8.dist-info/LICENSE
firstclass_dotenv-0.0.8.dist-info/METADATA
firstclass_dotenv-0.0.8.dist-info/WHEEL
firstclass_dotenv-0.0.8.dist-info/top_level.txt
firstclass_dotenv-0.0.8.dist-info/RECORD
