Metadata-Version: 2.1
Name: firstclass-dotenv
Version: 0.0.8
Summary: Read value of .env(dotenv) into ENV values
Home-page: https://github.com/hikarine3/firstclass_dotenv
Author: Hajime Kurita
Classifier: Programming Language :: Python :: 3
Classifier: License :: OSI Approved :: MIT License
Classifier: Operating System :: OS Independent
License-File: LICENSE
